paymentgrid/__init__.py
paymentgrid/action_codes/__init__.py
paymentgrid/action_codes/_standard_action_codes.py
paymentgrid/action_codes/mastercard.py
paymentgrid/action_codes/visa.py
paymentgrid-1.0.1.dist-info/LICENSE
paymentgrid-1.0.1.dist-info/METADATA
paymentgrid-1.0.1.dist-info/WHEEL
paymentgrid-1.0.1.dist-info/top_level.txt
paymentgrid-1.0.1.dist-info/RECORD
