Metadata-Version: 2.1
Name: paymentgrid
Version: 1.0.1
Summary: PaymentGrid Core (Python) is the foundational library for mapping credit card specific payment-related data.
Home-page: https://github.com/PaymentGrid/paymentgrid-core-python
Author: Ayesh Rodrigo
Author-email: paymentgrid.git@gmail.com
Classifier: Programming Language :: Python :: 3
Classifier: License :: OSI Approved :: MIT License
Classifier: Operating System :: OS Independent
Requires-Python: >=3.6
License-File: LICENSE
